MANIFEST.in
README.rst
setup.cfg
setup.py
architect/__init__.py
architect/celery.py
architect/context_processors.py
architect/exceptions.py
architect/schema.py
architect/settings.py
architect/urls.py
architect/utils.py
architect/views.py
architect/wsgi.py
architect/document/admin.py
architect/document/apps.py
architect/document/models.py
architect/document/schema.py
architect/document/transform.py
architect/document/urls.py
architect/document/views.py
architect/document/fixtures/sample_saltstack.json
architect/document/locale/cs/LC_MESSAGES/django.po
architect/document/locale/en/LC_MESSAGES/django.po
architect/document/management/__init__.py
architect/document/management/commands/__init__.py
architect/document/management/commands/sync_documents.py
architect/document/migrations/0001_initial.py
architect/document/migrations/__init__.py
architect/document/static/architect-document/js/d3-annotation.js
architect/document/static/architect-document/js/d3-annotation.js.map
architect/document/static/architect-document/js/d3-gauge.js
architect/document/static/architect-document/js/d3-legend.js
architect/document/static/architect-document/js/d3.layout.hive.js
architect/document/static/architect-document/js/d3.layout.matrix.js
architect/document/static/architect-document/js/d3.plot.arc.js
architect/document/static/architect-document/js/d3.plot.area.js
architect/document/static/architect-document/js/d3.plot.bar.js
architect/document/static/architect-document/js/d3.plot.bundle.js
architect/document/static/architect-document/js/d3.plot.force.js
architect/document/static/architect-document/js/d3.plot.gauge.js
architect/document/static/architect-document/js/d3.plot.hive.js
architect/document/static/architect-document/js/d3.plot.horizon.js
architect/document/static/architect-document/js/d3.plot.line.js
architect/document/static/architect-document/js/d3.plot.matrix.js
architect/document/static/architect-document/js/d3.plot.pack.js
architect_api.egg-info/PKG-INFO
architect_api.egg-info/SOURCES.txt
architect_api.egg-info/dependency_links.txt
architect_api.egg-info/requires.txt
architect_api.egg-info/top_level.txt
