Metadata-Version: 1.1
Name: architect-api
Version: 0.4
Summary: architect-api is a server API and UI of Architect, the service modeling, management and visualization platform.
Home-page: https://github.com/cznewt/architect-api/
Author: Aleš Komárek
Author-email: ales.komarek@newt.cz
License: Apache License, Version 2.0
Platform: UNKNOWN
Classifier: Intended Audience :: System Administrators
Classifier: License :: OSI Approved :: Apache Software License
Classifier: Operating System :: POSIX :: Linux
Classifier: Programming Language :: Python
Classifier: Programming Language :: Python :: Implementation :: CPython
Classifier: Programming Language :: Python :: 3
Classifier: Programming Language :: Python :: 3.6
